{"vm-4c8g-node2": [{"label": {"app": "buyservice", "pod-template-hash": "c989f4bd6"}, "name": "buyservice-c989f4bd6-28mnk", "spec": {"active_deadline_seconds": null, "affinity": {"node_affinity": {"preferred_during_scheduling_ignored_during_execution": null, "required_during_scheduling_ignored_during_execution": {"node_selector_terms": [{"match_expressions": [{"key": "kubernetes.io/hostname", "operator": "In", "values": ["vm-4c8g-node2"]}], "match_fields": null}]}}, "pod_affinity": null, "pod_anti_affinity": null}, "automount_service_account_token": null, "containers": [{"args": ["-c", "cd /go/src;go run main.go"], "command": ["/bin/bash"], "env": null, "env_from": null, "image": "vm-2c4g-registry:5000/buyservice:v0.0.1-scalling", "image_pull_policy": "IfNotPresent", "lifecycle": null, "liveness_probe": {"_exec": null, "failure_threshold": 3, "http_get": {"host": null, "http_headers": null, "path": "/qos", "port": 8080, "scheme": "HTTP"}, "initial_delay_seconds": 10, "period_seconds": 10, "success_threshold": 1, "tcp_socket": null, "timeout_seconds": 1}, "name": "buyservice", "ports": [{"container_port": 8080, "host_ip": null, "host_port": null, "name": null, "protocol": "TCP"}], "readiness_probe": {"_exec": null, "failure_threshold": 3, "http_get": {"host": null, "http_headers": null, "path": "/qos", "port": 8080, "scheme": "HTTP"}, "initial_delay_seconds": 10, "period_seconds": 10, "success_threshold": 1, "tcp_socket": null, "timeout_seconds": 1}, "resources": {"limits": null, "requests": null}, "security_context": null, "startup_probe": null, "stdin": null, "stdin_once": null, "termination_message_path": "/dev/termination-log", "termination_message_policy": "File", "tty": null, "volume_devices": null, "volume_mounts": [{"mount_path": "/var/run/secrets/kubernetes.io/serviceaccount", "mount_propagation": null, "name": "kube-api-access-vnnbq", "read_only": true, "sub_path": null, "sub_path_expr": null}], "working_dir": null}], "dns_config": null, "dns_policy": "ClusterFirst", "enable_service_links": true, "ephemeral_containers": null, "host_aliases": null, "host_ipc": null, "host_network": null, "host_pid": null, "hostname": null, "image_pull_secrets": null, "init_containers": null, "node_name": "vm-4c8g-node2", "node_selector": null, "overhead": null, "preemption_policy": "PreemptLowerPriority", "priority": 0, "priority_class_name": null, "readiness_gates": null, "restart_policy": "Always", "runtime_class_name": null, "scheduler_name": "default-scheduler", "security_context": {"fs_group": null, "fs_group_change_policy": null, "run_as_group": null, "run_as_non_root": null, "run_as_user": null, "se_linux_options": null, "seccomp_profile": null, "supplemental_groups": null, "sysctls": null, "windows_options": null}, "service_account": "default", "service_account_name": "default", "set_hostname_as_fqdn": null, "share_process_namespace": null, "subdomain": null, "termination_grace_period_seconds": 5, "tolerations": [{"effect": "NoExecute", "key": "predict", "operator": "Exists", "toleration_seconds": null, "value": null}, {"effect": "NoExecute", "key": "node.kubernetes.io/not-ready", "operator": "Exists", "toleration_seconds": 300, "value": null}, {"effect": "NoExecute", "key": "node.kubernetes.io/unreachable", "operator": "Exists", "toleration_seconds": 300, "value": null}], "topology_spread_constraints": null, "volumes": [{"aws_elastic_block_store": null, "azure_disk": null, "azure_file": null, "cephfs": null, "cinder": null, "config_map": null, "csi": null, "downward_api": null, "empty_dir": null, "ephemeral": null, "fc": null, "flex_volume": null, "flocker": null, "gce_persistent_disk": null, "git_repo": null, "glusterfs": null, "host_path": null, "iscsi": null, "name": "kube-api-access-vnnbq", "nfs": null, "persistent_volume_claim": null, "photon_persistent_disk": null, "portworx_volume": null, "projected": {"default_mode": 420, "sources": [{"config_map": null, "downward_api": null, "secret": null, "service_account_token": {"audience": null, "expiration_seconds": 3607, "path": "token"}}, {"config_map": {"items": [{"key": "ca.crt", "mode": null, "path": "ca.crt"}], "name": "kube-root-ca.crt", "optional": null}, "downward_api": null, "secret": null, "service_account_token": null}, {"config_map": null, "downward_api": {"items": [{"field_ref": {"api_version": "v1", "field_path": "metadata.namespace"}, "mode": null, "path": "namespace", "resource_field_ref": null}]}, "secret": null, "service_account_token": null}]}, "quobyte": null, "rbd": null, "scale_io": null, "secret": null, "storageos": null, "vsphere_volume": null}]}}, {"label": {"k8s-app": "influxdb", "pod-template-hash": "776b79db44", "task": "monitoring"}, "name": "influxdb-776b79db44-g668h", "spec": {"active_deadline_seconds": null, "affinity": null, "automount_service_account_token": null, "containers": [{"args": null, "command": null, "env": null, "env_from": null, "image": "influxdb:1.8", "image_pull_policy": "IfNotPresent", "lifecycle": null, "liveness_probe": null, "name": "influxdb", "ports": null, "readiness_probe": null, "resources": {"limits": null, "requests": null}, "security_context": null, "startup_probe": null, "stdin": null, "stdin_once": null, "termination_message_path": "/dev/termination-log", "termination_message_policy": "File", "tty": null, "volume_devices": null, "volume_mounts": [{"mount_path": "/var/lib/influxdb", "mount_propagation": null, "name": "influxdb-storage", "read_only": null, "sub_path": null, "sub_path_expr": null}, {"mount_path": "/var/run/secrets/kubernetes.io/serviceaccount", "mount_propagation": null, "name": "kube-api-access-k987j", "read_only": true, "sub_path": null, "sub_path_expr": null}], "working_dir": null}], "dns_config": null, "dns_policy": "ClusterFirst", "enable_service_links": true, "ephemeral_containers": null, "host_aliases": null, "host_ipc": null, "host_network": null, "host_pid": null, "hostname": null, "image_pull_secrets": null, "init_containers": null, "node_name": "vm-4c8g-node2", "node_selector": null, "overhead": null, "preemption_policy": "PreemptLowerPriority", "priority": 0, "priority_class_name": null, "readiness_gates": null, "restart_policy": "Always", "runtime_class_name": null, "scheduler_name": "default-scheduler", "security_context": {"fs_group": null, "fs_group_change_policy": null, "run_as_group": null, "run_as_non_root": null, "run_as_user": null, "se_linux_options": null, "seccomp_profile": null, "supplemental_groups": null, "sysctls": null, "windows_options": null}, "service_account": "default", "service_account_name": "default", "set_hostname_as_fqdn": null, "share_process_namespace": null, "subdomain": null, "termination_grace_period_seconds": 30, "tolerations": [{"effect": "NoExecute", "key": "predict", "operator": "Exists", "toleration_seconds": null, "value": null}, {"effect": "NoExecute", "key": "node.kubernetes.io/not-ready", "operator": "Exists", "toleration_seconds": 300, "value": null}, {"effect": "NoExecute", "key": "node.kubernetes.io/unreachable", "operator": "Exists", "toleration_seconds": 300, "value": null}], "topology_spread_constraints": null, "volumes": [{"aws_elastic_block_store": null, "azure_disk": null, "azure_file": null, "cephfs": null, "cinder": null, "config_map": null, "csi": null, "downward_api": null, "empty_dir": null, "ephemeral": null, "fc": null, "flex_volume": null, "flocker": null, "gce_persistent_disk": null, "git_repo": null, "glusterfs": null, "host_path": null, "iscsi": null, "name": "influxdb-storage", "nfs": null, "persistent_volume_claim": {"claim_name": "influxdb", "read_only": null}, "photon_persistent_disk": null, "portworx_volume": null, "projected": null, "quobyte": null, "rbd": null, "scale_io": null, "secret": null, "storageos": null, "vsphere_volume": null}, {"aws_elastic_block_store": null, "azure_disk": null, "azure_file": null, "cephfs": null, "cinder": null, "config_map": null, "csi": null, "downward_api": null, "empty_dir": null, "ephemeral": null, "fc": null, "flex_volume": null, "flocker": null, "gce_persistent_disk": null, "git_repo": null, "glusterfs": null, "host_path": null, "iscsi": null, "name": "kube-api-access-k987j", "nfs": null, "persistent_volume_claim": null, "photon_persistent_disk": null, "portworx_volume": null, "projected": {"default_mode": 420, "sources": [{"config_map": null, "downward_api": null, "secret": null, "service_account_token": {"audience": null, "expiration_seconds": 3607, "path": "token"}}, {"config_map": {"items": [{"key": "ca.crt", "mode": null, "path": "ca.crt"}], "name": "kube-root-ca.crt", "optional": null}, "downward_api": null, "secret": null, "service_account_token": null}, {"config_map": null, "downward_api": {"items": [{"field_ref": {"api_version": "v1", "field_path": "metadata.namespace"}, "mode": null, "path": "namespace", "resource_field_ref": null}]}, "secret": null, "service_account_token": null}]}, "quobyte": null, "rbd": null, "scale_io": null, "secret": null, "storageos": null, "vsphere_volume": null}]}}, {"label": {"app": "partservice", "pod-template-hash": "5f8f9bd749"}, "name": "partservice-5f8f9bd749-52pvl", "spec": {"active_deadline_seconds": null, "affinity": {"node_affinity": {"preferred_during_scheduling_ignored_during_execution": null, "required_during_scheduling_ignored_during_execution": {"node_selector_terms": [{"match_expressions": [{"key": "kubernetes.io/hostname", "operator": "In", "values": ["vm-4c8g-node2"]}], "match_fields": null}]}}, "pod_affinity": null, "pod_anti_affinity": null}, "automount_service_account_token": null, "containers": [{"args": ["-c", "cd /go/src; service mysql restart; mysql -u root < Init.sql;go run main.go"], "command": ["/bin/bash"], "env": null, "env_from": null, "image": "vm-2c4g-registry:5000/partservice:v0.0.1-scalling", "image_pull_policy": "IfNotPresent", "lifecycle": null, "liveness_probe": {"_exec": null, "failure_threshold": 3, "http_get": {"host": null, "http_headers": null, "path": "/qos", "port": 8080, "scheme": "HTTP"}, "initial_delay_seconds": 10, "period_seconds": 10, "success_threshold": 1, "tcp_socket": null, "timeout_seconds": 1}, "name": "partservice", "ports": [{"container_port": 8080, "host_ip": null, "host_port": null, "name": null, "protocol": "TCP"}], "readiness_probe": {"_exec": null, "failure_threshold": 3, "http_get": {"host": null, "http_headers": null, "path": "/qos", "port": 8080, "scheme": "HTTP"}, "initial_delay_seconds": 10, "period_seconds": 10, "success_threshold": 1, "tcp_socket": null, "timeout_seconds": 1}, "resources": {"limits": null, "requests": null}, "security_context": null, "startup_probe": null, "stdin": null, "stdin_once": null, "termination_message_path": "/dev/termination-log", "termination_message_policy": "File", "tty": null, "volume_devices": null, "volume_mounts": [{"mount_path": "/var/run/secrets/kubernetes.io/serviceaccount", "mount_propagation": null, "name": "kube-api-access-bh48r", "read_only": true, "sub_path": null, "sub_path_expr": null}], "working_dir": null}], "dns_config": null, "dns_policy": "ClusterFirst", "enable_service_links": true, "ephemeral_containers": null, "host_aliases": null, "host_ipc": null, "host_network": null, "host_pid": null, "hostname": null, "image_pull_secrets": null, "init_containers": null, "node_name": "vm-4c8g-node2", "node_selector": null, "overhead": null, "preemption_policy": "PreemptLowerPriority", "priority": 0, "priority_class_name": null, "readiness_gates": null, "restart_policy": "Always", "runtime_class_name": null, "scheduler_name": "default-scheduler", "security_context": {"fs_group": null, "fs_group_change_policy": null, "run_as_group": null, "run_as_non_root": null, "run_as_user": null, "se_linux_options": null, "seccomp_profile": null, "supplemental_groups": null, "sysctls": null, "windows_options": null}, "service_account": "default", "service_account_name": "default", "set_hostname_as_fqdn": null, "share_process_namespace": null, "subdomain": null, "termination_grace_period_seconds": 5, "tolerations": [{"effect": "NoExecute", "key": "predict", "operator": "Exists", "toleration_seconds": null, "value": null}, {"effect": "NoExecute", "key": "node.kubernetes.io/not-ready", "operator": "Exists", "toleration_seconds": 300, "value": null}, {"effect": "NoExecute", "key": "node.kubernetes.io/unreachable", "operator": "Exists", "toleration_seconds": 300, "value": null}], "topology_spread_constraints": null, "volumes": [{"aws_elastic_block_store": null, "azure_disk": null, "azure_file": null, "cephfs": null, "cinder": null, "config_map": null, "csi": null, "downward_api": null, "empty_dir": null, "ephemeral": null, "fc": null, "flex_volume": null, "flocker": null, "gce_persistent_disk": null, "git_repo": null, "glusterfs": null, "host_path": null, "iscsi": null, "name": "kube-api-access-bh48r", "nfs": null, "persistent_volume_claim": null, "photon_persistent_disk": null, "portworx_volume": null, "projected": {"default_mode": 420, "sources": [{"config_map": null, "downward_api": null, "secret": null, "service_account_token": {"audience": null, "expiration_seconds": 3607, "path": "token"}}, {"config_map": {"items": [{"key": "ca.crt", "mode": null, "path": "ca.crt"}], "name": "kube-root-ca.crt", "optional": null}, "downward_api": null, "secret": null, "service_account_token": null}, {"config_map": null, "downward_api": {"items": [{"field_ref": {"api_version": "v1", "field_path": "metadata.namespace"}, "mode": null, "path": "namespace", "resource_field_ref": null}]}, "secret": null, "service_account_token": null}]}, "quobyte": null, "rbd": null, "scale_io": null, "secret": null, "storageos": null, "vsphere_volume": null}]}}, {"label": {"app": "storageservice", "pod-template-hash": "69df9b8f8c"}, "name": "storageservice-69df9b8f8c-kx4hq", "spec": {"active_deadline_seconds": null, "affinity": {"node_affinity": {"preferred_during_scheduling_ignored_during_execution": null, "required_during_scheduling_ignored_during_execution": {"node_selector_terms": [{"match_expressions": [{"key": "kubernetes.io/hostname", "operator": "In", "values": ["vm-4c8g-node2"]}], "match_fields": null}]}}, "pod_affinity": null, "pod_anti_affinity": null}, "automount_service_account_token": null, "containers": [{"args": ["-c", "cd /go/src; service mysql restart; mysql -u root < Init.sql;go run main.go"], "command": ["/bin/bash"], "env": null, "env_from": null, "image": "vm-2c4g-registry:5000/storageservice:v0.0.1-scalling", "image_pull_policy": "IfNotPresent", "lifecycle": null, "liveness_probe": {"_exec": null, "failure_threshold": 3, "http_get": {"host": null, "http_headers": null, "path": "/qos", "port": 8080, "scheme": "HTTP"}, "initial_delay_seconds": 10, "period_seconds": 10, "success_threshold": 1, "tcp_socket": null, "timeout_seconds": 1}, "name": "storageservice", "ports": [{"container_port": 8080, "host_ip": null, "host_port": null, "name": null, "protocol": "TCP"}], "readiness_probe": {"_exec": null, "failure_threshold": 3, "http_get": {"host": null, "http_headers": null, "path": "/qos", "port": 8080, "scheme": "HTTP"}, "initial_delay_seconds": 10, "period_seconds": 10, "success_threshold": 1, "tcp_socket": null, "timeout_seconds": 1}, "resources": {"limits": null, "requests": null}, "security_context": null, "startup_probe": null, "stdin": null, "stdin_once": null, "termination_message_path": "/dev/termination-log", "termination_message_policy": "File", "tty": null, "volume_devices": null, "volume_mounts": [{"mount_path": "/var/run/secrets/kubernetes.io/serviceaccount", "mount_propagation": null, "name": "kube-api-access-t9v4d", "read_only": true, "sub_path": null, "sub_path_expr": null}], "working_dir": null}], "dns_config": null, "dns_policy": "ClusterFirst", "enable_service_links": true, "ephemeral_containers": null, "host_aliases": null, "host_ipc": null, "host_network": null, "host_pid": null, "hostname": null, "image_pull_secrets": null, "init_containers": null, "node_name": "vm-4c8g-node2", "node_selector": null, "overhead": null, "preemption_policy": "PreemptLowerPriority", "priority": 0, "priority_class_name": null, "readiness_gates": null, "restart_policy": "Always", "runtime_class_name": null, "scheduler_name": "default-scheduler", "security_context": {"fs_group": null, "fs_group_change_policy": null, "run_as_group": null, "run_as_non_root": null, "run_as_user": null, "se_linux_options": null, "seccomp_profile": null, "supplemental_groups": null, "sysctls": null, "windows_options": null}, "service_account": "default", "service_account_name": "default", "set_hostname_as_fqdn": null, "share_process_namespace": null, "subdomain": null, "termination_grace_period_seconds": 5, "tolerations": [{"effect": "NoExecute", "key": "predict", "operator": "Exists", "toleration_seconds": null, "value": null}, {"effect": "NoExecute", "key": "node.kubernetes.io/not-ready", "operator": "Exists", "toleration_seconds": 300, "value": null}, {"effect": "NoExecute", "key": "node.kubernetes.io/unreachable", "operator": "Exists", "toleration_seconds": 300, "value": null}], "topology_spread_constraints": null, "volumes": [{"aws_elastic_block_store": null, "azure_disk": null, "azure_file": null, "cephfs": null, "cinder": null, "config_map": null, "csi": null, "downward_api": null, "empty_dir": null, "ephemeral": null, "fc": null, "flex_volume": null, "flocker": null, "gce_persistent_disk": null, "git_repo": null, "glusterfs": null, "host_path": null, "iscsi": null, "name": "kube-api-access-t9v4d", "nfs": null, "persistent_volume_claim": null, "photon_persistent_disk": null, "portworx_volume": null, "projected": {"default_mode": 420, "sources": [{"config_map": null, "downward_api": null, "secret": null, "service_account_token": {"audience": null, "expiration_seconds": 3607, "path": "token"}}, {"config_map": {"items": [{"key": "ca.crt", "mode": null, "path": "ca.crt"}], "name": "kube-root-ca.crt", "optional": null}, "downward_api": null, "secret": null, "service_account_token": null}, {"config_map": null, "downward_api": {"items": [{"field_ref": {"api_version": "v1", "field_path": "metadata.namespace"}, "mode": null, "path": "namespace", "resource_field_ref": null}]}, "secret": null, "service_account_token": null}]}, "quobyte": null, "rbd": null, "scale_io": null, "secret": null, "storageos": null, "vsphere_volume": null}]}}, {"label": {"app": "webapp", "pod-template-hash": "d5585d547"}, "name": "webapp-d5585d547-kzqn8", "spec": {"active_deadline_seconds": null, "affinity": null, "automount_service_account_token": null, "containers": [{"args": null, "command": null, "env": null, "env_from": null, "image": "beekman9527/webapp", "image_pull_policy": "Always", "lifecycle": null, "liveness_probe": null, "name": "webapp", "ports": [{"container_port": 8080, "host_ip": null, "host_port": null, "name": null, "protocol": "TCP"}], "readiness_probe": null, "resources": {"limits": {"cpu": "1", "memory": "1000Mi"}, "requests": {"cpu": "500m", "memory": "500Mi"}}, "security_context": null, "startup_probe": null, "stdin": null, "stdin_once": null, "termination_message_path": "/dev/termination-log", "termination_message_policy": "File", "tty": null, "volume_devices": null, "volume_mounts": [{"mount_path": "/var/run/secrets/kubernetes.io/serviceaccount", "mount_propagation": null, "name": "kube-api-access-x8qlv", "read_only": true, "sub_path": null, "sub_path_expr": null}], "working_dir": null}], "dns_config": null, "dns_policy": "ClusterFirst", "enable_service_links": true, "ephemeral_containers": null, "host_aliases": null, "host_ipc": null, "host_network": null, "host_pid": null, "hostname": null, "image_pull_secrets": null, "init_containers": null, "node_name": "vm-4c8g-node2", "node_selector": null, "overhead": null, "preemption_policy": "PreemptLowerPriority", "priority": 0, "priority_class_name": null, "readiness_gates": null, "restart_policy": "Always", "runtime_class_name": null, "scheduler_name": "default-scheduler", "security_context": {"fs_group": null, "fs_group_change_policy": null, "run_as_group": null, "run_as_non_root": null, "run_as_user": null, "se_linux_options": null, "seccomp_profile": null, "supplemental_groups": null, "sysctls": null, "windows_options": null}, "service_account": "default", "service_account_name": "default", "set_hostname_as_fqdn": null, "share_process_namespace": null, "subdomain": null, "termination_grace_period_seconds": 30, "tolerations": [{"effect": "NoExecute", "key": "predict", "operator": "Exists", "toleration_seconds": null, "value": null}, {"effect": "NoExecute", "key": "node.kubernetes.io/not-ready", "operator": "Exists", "toleration_seconds": 300, "value": null}, {"effect": "NoExecute", "key": "node.kubernetes.io/unreachable", "operator": "Exists", "toleration_seconds": 300, "value": null}], "topology_spread_constraints": null, "volumes": [{"aws_elastic_block_store": null, "azure_disk": null, "azure_file": null, "cephfs": null, "cinder": null, "config_map": null, "csi": null, "downward_api": null, "empty_dir": null, "ephemeral": null, "fc": null, "flex_volume": null, "flocker": null, "gce_persistent_disk": null, "git_repo": null, "glusterfs": null, "host_path": null, "iscsi": null, "name": "kube-api-access-x8qlv", "nfs": null, "persistent_volume_claim": null, "photon_persistent_disk": null, "portworx_volume": null, "projected": {"default_mode": 420, "sources": [{"config_map": null, "downward_api": null, "secret": null, "service_account_token": {"audience": null, "expiration_seconds": 3607, "path": "token"}}, {"config_map": {"items": [{"key": "ca.crt", "mode": null, "path": "ca.crt"}], "name": "kube-root-ca.crt", "optional": null}, "downward_api": null, "secret": null, "service_account_token": null}, {"config_map": null, "downward_api": {"items": [{"field_ref": {"api_version": "v1", "field_path": "metadata.namespace"}, "mode": null, "path": "namespace", "resource_field_ref": null}]}, "secret": null, "service_account_token": null}]}, "quobyte": null, "rbd": null, "scale_io": null, "secret": null, "storageos": null, "vsphere_volume": null}]}}], "vm-4c8g-node3": [{"label": {"app": "storageservice-1", "pod-template-hash": "9585bfc6b"}, "name": "storageservice-1-9585bfc6b-g8spv", "spec": {"active_deadline_seconds": null, "affinity": {"node_affinity": {"preferred_during_scheduling_ignored_during_execution": null, "required_during_scheduling_ignored_during_execution": {"node_selector_terms": [{"match_expressions": [{"key": "kubernetes.io/hostname", "operator": "In", "values": ["vm-4c8g-node3"]}], "match_fields": null}]}}, "pod_affinity": null, "pod_anti_affinity": null}, "automount_service_account_token": null, "containers": [{"args": ["-c", "cd /go/src; service mysql restart; mysql -u root < Init.sql;go run main.go"], "command": ["/bin/bash"], "env": null, "env_from": null, "image": "vm-2c4g-registry:5000/storageservice:v0.0.1-scalling", "image_pull_policy": "IfNotPresent", "lifecycle": null, "liveness_probe": {"_exec": null, "failure_threshold": 3, "http_get": {"host": null, "http_headers": null, "path": "/qos", "port": 8080, "scheme": "HTTP"}, "initial_delay_seconds": 10, "period_seconds": 10, "success_threshold": 1, "tcp_socket": null, "timeout_seconds": 1}, "name": "storageservice-1", "ports": [{"container_port": 8080, "host_ip": null, "host_port": null, "name": null, "protocol": "TCP"}], "readiness_probe": {"_exec": null, "failure_threshold": 3, "http_get": {"host": null, "http_headers": null, "path": "/qos", "port": 8080, "scheme": "HTTP"}, "initial_delay_seconds": 10, "period_seconds": 10, "success_threshold": 1, "tcp_socket": null, "timeout_seconds": 1}, "resources": {"limits": null, "requests": null}, "security_context": null, "startup_probe": null, "stdin": null, "stdin_once": null, "termination_message_path": "/dev/termination-log", "termination_message_policy": "File", "tty": null, "volume_devices": null, "volume_mounts": [{"mount_path": "/var/run/secrets/kubernetes.io/serviceaccount", "mount_propagation": null, "name": "kube-api-access-wdfbc", "read_only": true, "sub_path": null, "sub_path_expr": null}], "working_dir": null}], "dns_config": null, "dns_policy": "ClusterFirst", "enable_service_links": true, "ephemeral_containers": null, "host_aliases": null, "host_ipc": null, "host_network": null, "host_pid": null, "hostname": null, "image_pull_secrets": null, "init_containers": null, "node_name": "vm-4c8g-node3", "node_selector": null, "overhead": null, "preemption_policy": "PreemptLowerPriority", "priority": 0, "priority_class_name": null, "readiness_gates": null, "restart_policy": "Always", "runtime_class_name": null, "scheduler_name": "default-scheduler", "security_context": {"fs_group": null, "fs_group_change_policy": null, "run_as_group": null, "run_as_non_root": null, "run_as_user": null, "se_linux_options": null, "seccomp_profile": null, "supplemental_groups": null, "sysctls": null, "windows_options": null}, "service_account": "default", "service_account_name": "default", "set_hostname_as_fqdn": null, "share_process_namespace": null, "subdomain": null, "termination_grace_period_seconds": 5, "tolerations": [{"effect": "NoExecute", "key": "predict", "operator": "Exists", "toleration_seconds": null, "value": null}, {"effect": "NoExecute", "key": "node.kubernetes.io/not-ready", "operator": "Exists", "toleration_seconds": 300, "value": null}, {"effect": "NoExecute", "key": "node.kubernetes.io/unreachable", "operator": "Exists", "toleration_seconds": 300, "value": null}], "topology_spread_constraints": null, "volumes": [{"aws_elastic_block_store": null, "azure_disk": null, "azure_file": null, "cephfs": null, "cinder": null, "config_map": null, "csi": null, "downward_api": null, "empty_dir": null, "ephemeral": null, "fc": null, "flex_volume": null, "flocker": null, "gce_persistent_disk": null, "git_repo": null, "glusterfs": null, "host_path": null, "iscsi": null, "name": "kube-api-access-wdfbc", "nfs": null, "persistent_volume_claim": null, "photon_persistent_disk": null, "portworx_volume": null, "projected": {"default_mode": 420, "sources": [{"config_map": null, "downward_api": null, "secret": null, "service_account_token": {"audience": null, "expiration_seconds": 3607, "path": "token"}}, {"config_map": {"items": [{"key": "ca.crt", "mode": null, "path": "ca.crt"}], "name": "kube-root-ca.crt", "optional": null}, "downward_api": null, "secret": null, "service_account_token": null}, {"config_map": null, "downward_api": {"items": [{"field_ref": {"api_version": "v1", "field_path": "metadata.namespace"}, "mode": null, "path": "namespace", "resource_field_ref": null}]}, "secret": null, "service_account_token": null}]}, "quobyte": null, "rbd": null, "scale_io": null, "secret": null, "storageos": null, "vsphere_volume": null}]}}, {"label": {"app": "tableservice", "pod-template-hash": "f64f7b4b7"}, "name": "tableservice-f64f7b4b7-qwn5h", "spec": {"active_deadline_seconds": null, "affinity": {"node_affinity": {"preferred_during_scheduling_ignored_during_execution": null, "required_during_scheduling_ignored_during_execution": {"node_selector_terms": [{"match_expressions": [{"key": "kubernetes.io/hostname", "operator": "In", "values": ["vm-4c8g-node3"]}], "match_fields": null}]}}, "pod_affinity": null, "pod_anti_affinity": null}, "automount_service_account_token": null, "containers": [{"args": ["-c", "cd /go/src;go run main.go"], "command": ["/bin/bash"], "env": null, "env_from": null, "image": "vm-2c4g-registry:5000/tableservice:v0.0.1-scalling", "image_pull_policy": "IfNotPresent", "lifecycle": null, "liveness_probe": {"_exec": null, "failure_threshold": 3, "http_get": {"host": null, "http_headers": null, "path": "/qos", "port": 8080, "scheme": "HTTP"}, "initial_delay_seconds": 10, "period_seconds": 10, "success_threshold": 1, "tcp_socket": null, "timeout_seconds": 1}, "name": "tableservice", "ports": [{"container_port": 8080, "host_ip": null, "host_port": null, "name": null, "protocol": "TCP"}], "readiness_probe": {"_exec": null, "failure_threshold": 3, "http_get": {"host": null, "http_headers": null, "path": "/qos", "port": 8080, "scheme": "HTTP"}, "initial_delay_seconds": 10, "period_seconds": 10, "success_threshold": 1, "tcp_socket": null, "timeout_seconds": 1}, "resources": {"limits": null, "requests": null}, "security_context": null, "startup_probe": null, "stdin": null, "stdin_once": null, "termination_message_path": "/dev/termination-log", "termination_message_policy": "File", "tty": null, "volume_devices": null, "volume_mounts": [{"mount_path": "/var/run/secrets/kubernetes.io/serviceaccount", "mount_propagation": null, "name": "kube-api-access-6j2jh", "read_only": true, "sub_path": null, "sub_path_expr": null}], "working_dir": null}], "dns_config": null, "dns_policy": "ClusterFirst", "enable_service_links": true, "ephemeral_containers": null, "host_aliases": null, "host_ipc": null, "host_network": null, "host_pid": null, "hostname": null, "image_pull_secrets": null, "init_containers": null, "node_name": "vm-4c8g-node3", "node_selector": null, "overhead": null, "preemption_policy": "PreemptLowerPriority", "priority": 0, "priority_class_name": null, "readiness_gates": null, "restart_policy": "Always", "runtime_class_name": null, "scheduler_name": "default-scheduler", "security_context": {"fs_group": null, "fs_group_change_policy": null, "run_as_group": null, "run_as_non_root": null, "run_as_user": null, "se_linux_options": null, "seccomp_profile": null, "supplemental_groups": null, "sysctls": null, "windows_options": null}, "service_account": "default", "service_account_name": "default", "set_hostname_as_fqdn": null, "share_process_namespace": null, "subdomain": null, "termination_grace_period_seconds": 5, "tolerations": [{"effect": "NoExecute", "key": "predict", "operator": "Exists", "toleration_seconds": null, "value": null}, {"effect": "NoExecute", "key": "node.kubernetes.io/not-ready", "operator": "Exists", "toleration_seconds": 300, "value": null}, {"effect": "NoExecute", "key": "node.kubernetes.io/unreachable", "operator": "Exists", "toleration_seconds": 300, "value": null}], "topology_spread_constraints": null, "volumes": [{"aws_elastic_block_store": null, "azure_disk": null, "azure_file": null, "cephfs": null, "cinder": null, "config_map": null, "csi": null, "downward_api": null, "empty_dir": null, "ephemeral": null, "fc": null, "flex_volume": null, "flocker": null, "gce_persistent_disk": null, "git_repo": null, "glusterfs": null, "host_path": null, "iscsi": null, "name": "kube-api-access-6j2jh", "nfs": null, "persistent_volume_claim": null, "photon_persistent_disk": null, "portworx_volume": null, "projected": {"default_mode": 420, "sources": [{"config_map": null, "downward_api": null, "secret": null, "service_account_token": {"audience": null, "expiration_seconds": 3607, "path": "token"}}, {"config_map": {"items": [{"key": "ca.crt", "mode": null, "path": "ca.crt"}], "name": "kube-root-ca.crt", "optional": null}, "downward_api": null, "secret": null, "service_account_token": null}, {"config_map": null, "downward_api": {"items": [{"field_ref": {"api_version": "v1", "field_path": "metadata.namespace"}, "mode": null, "path": "namespace", "resource_field_ref": null}]}, "secret": null, "service_account_token": null}]}, "quobyte": null, "rbd": null, "scale_io": null, "secret": null, "storageos": null, "vsphere_volume": null}]}}, {"label": {"app": "timeservice", "pod-template-hash": "7fcb68698b"}, "name": "timeservice-7fcb68698b-qv4mg", "spec": {"active_deadline_seconds": null, "affinity": {"node_affinity": {"preferred_during_scheduling_ignored_during_execution": null, "required_during_scheduling_ignored_during_execution": {"node_selector_terms": [{"match_expressions": [{"key": "kubernetes.io/hostname", "operator": "In", "values": ["vm-4c8g-node3"]}], "match_fields": null}]}}, "pod_affinity": null, "pod_anti_affinity": null}, "automount_service_account_token": null, "containers": [{"args": ["-c", "cd /go/src;go run main.go"], "command": ["/bin/bash"], "env": null, "env_from": null, "image": "vm-2c4g-registry:5000/timeservice:v0.0.1-scalling", "image_pull_policy": "IfNotPresent", "lifecycle": null, "liveness_probe": {"_exec": null, "failure_threshold": 3, "http_get": {"host": null, "http_headers": null, "path": "/qos", "port": 8080, "scheme": "HTTP"}, "initial_delay_seconds": 10, "period_seconds": 10, "success_threshold": 1, "tcp_socket": null, "timeout_seconds": 1}, "name": "timeservice", "ports": [{"container_port": 8080, "host_ip": null, "host_port": null, "name": null, "protocol": "TCP"}], "readiness_probe": {"_exec": null, "failure_threshold": 3, "http_get": {"host": null, "http_headers": null, "path": "/qos", "port": 8080, "scheme": "HTTP"}, "initial_delay_seconds": 10, "period_seconds": 10, "success_threshold": 1, "tcp_socket": null, "timeout_seconds": 1}, "resources": {"limits": null, "requests": null}, "security_context": null, "startup_probe": null, "stdin": null, "stdin_once": null, "termination_message_path": "/dev/termination-log", "termination_message_policy": "File", "tty": null, "volume_devices": null, "volume_mounts": [{"mount_path": "/var/run/secrets/kubernetes.io/serviceaccount", "mount_propagation": null, "name": "kube-api-access-skqw5", "read_only": true, "sub_path": null, "sub_path_expr": null}], "working_dir": null}], "dns_config": null, "dns_policy": "ClusterFirst", "enable_service_links": true, "ephemeral_containers": null, "host_aliases": null, "host_ipc": null, "host_network": null, "host_pid": null, "hostname": null, "image_pull_secrets": null, "init_containers": null, "node_name": "vm-4c8g-node3", "node_selector": null, "overhead": null, "preemption_policy": "PreemptLowerPriority", "priority": 0, "priority_class_name": null, "readiness_gates": null, "restart_policy": "Always", "runtime_class_name": null, "scheduler_name": "default-scheduler", "security_context": {"fs_group": null, "fs_group_change_policy": null, "run_as_group": null, "run_as_non_root": null, "run_as_user": null, "se_linux_options": null, "seccomp_profile": null, "supplemental_groups": null, "sysctls": null, "windows_options": null}, "service_account": "default", "service_account_name": "default", "set_hostname_as_fqdn": null, "share_process_namespace": null, "subdomain": null, "termination_grace_period_seconds": 5, "tolerations": [{"effect": "NoExecute", "key": "predict", "operator": "Exists", "toleration_seconds": null, "value": null}, {"effect": "NoExecute", "key": "node.kubernetes.io/not-ready", "operator": "Exists", "toleration_seconds": 300, "value": null}, {"effect": "NoExecute", "key": "node.kubernetes.io/unreachable", "operator": "Exists", "toleration_seconds": 300, "value": null}], "topology_spread_constraints": null, "volumes": [{"aws_elastic_block_store": null, "azure_disk": null, "azure_file": null, "cephfs": null, "cinder": null, "config_map": null, "csi": null, "downward_api": null, "empty_dir": null, "ephemeral": null, "fc": null, "flex_volume": null, "flocker": null, "gce_persistent_disk": null, "git_repo": null, "glusterfs": null, "host_path": null, "iscsi": null, "name": "kube-api-access-skqw5", "nfs": null, "persistent_volume_claim": null, "photon_persistent_disk": null, "portworx_volume": null, "projected": {"default_mode": 420, "sources": [{"config_map": null, "downward_api": null, "secret": null, "service_account_token": {"audience": null, "expiration_seconds": 3607, "path": "token"}}, {"config_map": {"items": [{"key": "ca.crt", "mode": null, "path": "ca.crt"}], "name": "kube-root-ca.crt", "optional": null}, "downward_api": null, "secret": null, "service_account_token": null}, {"config_map": null, "downward_api": {"items": [{"field_ref": {"api_version": "v1", "field_path": "metadata.namespace"}, "mode": null, "path": "namespace", "resource_field_ref": null}]}, "secret": null, "service_account_token": null}]}, "quobyte": null, "rbd": null, "scale_io": null, "secret": null, "storageos": null, "vsphere_volume": null}]}}]}